up_fmap/__init__.py
up_fmap/fmap_planner.py
up_fmap/FMAP/FMAP.jar
up_fmap-0.0.13.dist-info/LICENSE
up_fmap-0.0.13.dist-info/METADATA
up_fmap-0.0.13.dist-info/WHEEL
up_fmap-0.0.13.dist-info/top_level.txt
up_fmap-0.0.13.dist-info/RECORD
