Metadata-Version: 2.1
Name: up-fmap
Version: 0.0.13
Summary: up_fmap
Home-page: UNKNOWN
Author: Alejandro Torreño, Eva Onaindia and Oscar Sapena
Author-email: onaindia@dsic.upv.es
License: APACHE
Platform: UNKNOWN
